.DS_Store
farewelltyson/.DS_Store
farewelltyson/__init__.py
farewelltyson/achieve.py
farewelltyson/adventure.py
farewelltyson/all_data.csv
farewelltyson/analyze.py
farewelltyson/bake.py
farewelltyson/budget.py
farewelltyson/build_it.py
farewelltyson/buy_packs.py
farewelltyson/camp.py
farewelltyson/celebrate.py
farewelltyson/chat.py
farewelltyson/check_your_balance.py
farewelltyson/clean.py
farewelltyson/climb.py
farewelltyson/code.py
farewelltyson/collaborate.py
farewelltyson/communicate.py
farewelltyson/compete.py
farewelltyson/cook.py
farewelltyson/create.py
farewelltyson/cry.py
farewelltyson/dance.py
farewelltyson/debate.py
farewelltyson/debug.py
farewelltyson/design.py
farewelltyson/discuss.py
farewelltyson/document.py
farewelltyson/draw.py
farewelltyson/dream.py
farewelltyson/drive.py
farewelltyson/eat.py
farewelltyson/edit.py
farewelltyson/exercise.py
farewelltyson/explore.py
farewelltyson/filename.py
farewelltyson/film.py
farewelltyson/fish.py
farewelltyson/fly.py
farewelltyson/follow.py
farewelltyson/get_the_data.py
farewelltyson/give.py
farewelltyson/help.py
farewelltyson/hug.py
farewelltyson/hunt.py
farewelltyson/imagine.py
farewelltyson/improve.py
farewelltyson/innovate.py
farewelltyson/invent.py
farewelltyson/invest.py
farewelltyson/jump.py
farewelltyson/kiss.py
farewelltyson/laugh.py
farewelltyson/lead.py
farewelltyson/learn.py
farewelltyson/listen.py
farewelltyson/login.py
farewelltyson/lose.py
farewelltyson/manage.py
farewelltyson/meditate.py
farewelltyson/mentor.py
farewelltyson/negotiate.py
farewelltyson/network.py
farewelltyson/new_data.py
farewelltyson/open_packs.py
farewelltyson/organize.py
farewelltyson/paint.py
farewelltyson/party.py
farewelltyson/plan.py
farewelltyson/plant.py
farewelltyson/play.py
farewelltyson/pray.py
farewelltyson/program.py
farewelltyson/publish.py
farewelltyson/race.py
farewelltyson/read.py
farewelltyson/receive.py
farewelltyson/relax.py
farewelltyson/ride.py
farewelltyson/run.py
farewelltyson/save.py
farewelltyson-0.0.16.dist-info/METADATA
farewelltyson-0.0.16.dist-info/WHEEL
farewelltyson-0.0.16.dist-info/top_level.txt
farewelltyson-0.0.16.dist-info/RECORD
