Metadata-Version: 2.1
Name: farewelltyson
Version: 0.0.16
Summary: For Tyson
Author: Jordan
Author-email: 
Keywords: python,tyson,message,bye,goodbye
Classifier: Development Status :: 1 - Planning
Classifier: Intended Audience :: Developers
Classifier: Programming Language :: Python :: 3
Classifier: Operating System :: Unix
Classifier: Operating System :: MacOS :: MacOS X
Classifier: Operating System :: Microsoft :: Windows
Requires-Dist: pandas
Requires-Dist: importlib
